pyhnsw.cpython-39-x86_64-linux-gnu.so
pyhnsw-0.1.0.dist-info/METADATA
pyhnsw-0.1.0.dist-info/RECORD
pyhnsw-0.1.0.dist-info/top_level.txt
pyhnsw-0.1.0.dist-info/WHEEL
