Metadata-Version: 2.4
Name: pyhnsw
Version: 0.1.0
Summary: Python bindings for HNSW (Hierarchical Navigable Small World) vector search
Author: Your Name
Author-email: Your Name <your.email@example.com>
License: MIT
Requires-Python: >=3.7
Requires-Dist: numpy>=1.19.0
Provides-Extra: test
Requires-Dist: pytest>=6.0; extra == "test"
Requires-Dist: pytest-benchmark; extra == "test"
Dynamic: author
Dynamic: requires-python
